[
  {
    "originator": "Simon McVittie <smcv@debian.org>",
    "subject": "0ad: assertion failure if hyperthreading (SMT) is supported but disabled",
    "msgid": "<YkG+2KrwK0rqX4A0@momentum.pseudorandom.co.uk>",
    "package": "0ad",
    "severity": "normal",
    "owner": "",
    "summary": "",
    "location": "db-h",
    "source": "0ad",
    "pending": "pending",
    "forwarded": "",
    "found_versions": [
      "0ad/0.0.25b-1.1"
    ],
    "fixed_versions": [],
    "date": "2022-03-28T14:00:01",
    "log_modified": "2022-05-27T08:18:03",
    "tags": [],
    "done": false,
    "done_by": null,
    "archived": false,
    "unarchived": false,
    "bug_num": 1008531,
    "mergedwith": [],
    "blockedby": [],
    "blocks": [],
    "affects": []
  },
  {
    "originator": "Lennart Weller <lhw@ring0.de>",
    "subject": "0ad: Test 0ad with new version of nvidia-texture-tools",
    "msgid": "<20150804125612.30208.90988.reportbug@lhw.ring0.de>",
    "package": "0ad",
    "severity": "wishlist",
    "owner": "",
    "summary": "",
    "location": "db-h",
    "source": "0ad",
    "pending": "pending",
    "forwarded": "",
    "found_versions": [],
    "fixed_versions": [],
    "date": "2015-08-04T13:00:01",
    "log_modified": "2021-03-07T21:39:04",
    "tags": [],
    "done": false,
    "done_by": null,
    "archived": false,
    "unarchived": false,
    "bug_num": 794562,
    "mergedwith": [],
    "blockedby": [],
    "blocks": [],
    "affects": []
  },
  {
    "originator": "\"David W. Kennedy\" <dave_k@reasoned.us>",
    "subject": "Manpage is missing documentation of many command line arguments",
    "msgid": "<9e115d3fa68b854d22e88bbf9e77172b@reasoned.us>",
    "package": "0ad",
    "severity": "wishlist",
    "owner": "",
    "summary": "",
    "location": "db-h",
    "source": "0ad",
    "pending": "pending",
    "forwarded": "",
    "found_versions": [
      "0ad/0.0.23.1-5",
      "0ad/0.0.24b-1"
    ],
    "fixed_versions": [],
    "date": "2021-08-12T23:00:02",
    "log_modified": "2021-08-12T23:12:02",
    "tags": [],
    "done": false,
    "done_by": null,
    "archived": false,
    "unarchived": false,
    "bug_num": 992135,
    "mergedwith": [],
    "blockedby": [],
    "blocks": [],
    "affects": []
  },
  {
    "originator": "Aurelien Jarno <aurel32@debian.org>",
    "subject": "0xffff: please switch to libusb 1.0",
    "msgid": "<20160108183429.GA431@aurel32.net>",
    "package": "0xffff",
    "severity": "wishlist",
    "owner": "",
    "summary": "",
    "location": "db-h",
    "source": "0xffff",
    "pending": "pending",
    "forwarded": "",
    "found_versions": [
      "0xffff/0.6.1-3"
    ],
    "fixed_versions": [
      "0xffff/0.6.1+git20160627-1"
    ],
    "date": "2016-01-08T18:39:02",
    "log_modified": "2016-12-07T01:33:05",
    "tags": [],
    "done": false,
    "done_by": null,
    "archived": false,
    "unarchived": false,
    "bug_num": 810392,
    "mergedwith": [],
    "blockedby": [],
    "blocks": [
      810470
    ],
    "affects": []
  },
  {
    "originator": "Russell Coker <russell@coker.com.au>",
    "subject": "2048-qt: doesn't scale to lower resolution displays",
    "msgid": "<169979292017.2.16074731501482275325.reportbug@pine>",
    "package": "2048-qt",
    "severity": "normal",
    "owner": "",
    "summary": "",
    "location": "db-h",
    "source": "2048-qt",
    "pending": "pending",
    "forwarded": "",
    "found_versions": [
      "2048-qt/0.1.6-2"
    ],
    "fixed_versions": [],
    "date": "2023-11-12T12:45:02",
    "log_modified": "2023-11-12T12:57:02",
    "tags": [
      "upstream"
    ],
    "done": false,
    "done_by": null,
    "archived": false,
    "unarchived": false,
    "bug_num": 1055834,
    "mergedwith": [],
    "blockedby": [],
    "blocks": [],
    "affects": []
  },
  {
    "originator": "Russell Coker <russell@coker.com.au>",
    "subject": "2048-qt: wish this had support for touch displays",
    "msgid": "<169979312604.2.9314426182018217202.reportbug@pine>",
    "package": "2048-qt",
    "severity": "normal",
    "owner": "",
    "summary": "",
    "location": "db-h",
    "source": "2048-qt",
    "pending": "pending",
    "forwarded": "",
    "found_versions": [
      "2048-qt/0.1.6-2"
    ],
    "fixed_versions": [],
    "date": "2023-11-12T12:48:01",
    "log_modified": "2023-11-12T12:48:04",
    "tags": [],
    "done": false,
    "done_by": null,
    "archived": false,
    "unarchived": false,
    "bug_num": 1055836,
    "mergedwith": [],
    "blockedby": [],
    "blocks": [],
    "affects": []
  },
  {
    "originator": "Axel Beckert <abe@debian.org>",
    "subject": "2048-qt: Segfaults on startup",
    "msgid": "<877g5l3ga1.fsf@kiva6.ethz.ch>",
    "package": "2048-qt",
    "severity": "important",
    "owner": "",
    "summary": "",
    "location": "db-h",
    "source": "2048-qt",
    "pending": "pending",
    "forwarded": "",
    "found_versions": [
      "2048-qt/0.1.4-3"
    ],
    "fixed_versions": [],
    "date": "2014-05-16T15:21:01",
    "log_modified": "2019-02-08T19:06:03",
    "tags": [],
    "done": false,
